mcp_weather_http/__init__.py
mcp_weather_http/__main__.py
mcp_weather_http/server.py
mcp_weather_http_lqh-1.1.0.dist-info/METADATA
mcp_weather_http_lqh-1.1.0.dist-info/WHEEL
mcp_weather_http_lqh-1.1.0.dist-info/entry_points.txt
mcp_weather_http_lqh-1.1.0.dist-info/top_level.txt
mcp_weather_http_lqh-1.1.0.dist-info/RECORD
